{
    "Brightness": 0,
    "Contrast": 0.9,
    "Saturation": 1.1,
    "Sharpness": 1.1,
    "ColourTemperature": 3600,
    "ColourGains": 0,
    "ExposureTime": 5213,
    "ExposureValue": 0,
    "AnalogueGain": 1.12,
    "AeFlickerPeriod": 500100,
    "LensPosition": 0,
    "SyncFrames": 500001,
    "AfWindows": null,
    "FrameDurationLimits": null,
    "ScalerCrop": null,
    "AwbEnable": true,
    "AeEnable": true,
    "AfTrigger": false,
    "StatsOutputEnable": false,
    "CnnEnableInputTensor": false,
    "AwbMode": "0",
    "AeExposureMode": "0",
    "AeConstraintMode": "0",
    "AeMeteringMode": "0",
    "AeFlickerMode": "1",
    "NoiseReductionMode": "4",
    "HdrMode": "0",
    "AfMode": "2",
    "AfRange": "0",
    "AfSpeed": "0",
    "AfMetering": "0",
    "AfPause": "2",
    "SyncMode": "0",
    "ExposureTimeMode": "0",
    "AnalogueGainMode": "0",
    "resolution": "1920x1080",
    "fps": "30",
    "modo": "Stream",
    "bitrate": "10M",
    "preset": "superfast",
    "protocolo_stream": "SRT",
    "hdmi": "Off",
    "IPDestino": "rtsp://192.168.0.15:8554/cam",
    "IPSDP": "0.0.0.0",
    "protocolo": "tcp",
    "IPDestinoSRT": "192.168.0.15",
    "puertoDestinoSRT": "8890",
    "extraDataSRT": "?streamid=publish:cam&mode=caller&transtype=live&latency=0",
    "mic": "plughw:Device,0"
}